litbee/__init__.py
litbee/__main__.py
litbee/__main__.py-
litbee/app.py
litbee/color_map.py
litbee/fetch_paste.py
litbee/fetch_upload.py
litbee/fetch_upload.py-
litbee/fetch_urls.py
litbee/files2df.py
litbee/home.py
litbee/info.py
litbee/litbee.py
litbee/multipage.py
litbee/options.py-
litbee/process_upload.py
litbee/settings.py
litbee/t2s.py
litbee/url2txt.py
litbee/utils.py
litbee/xbee_page.py
litbee-0.1.2.dist-info/entry_points.txt
litbee-0.1.2.dist-info/LICENSE
litbee-0.1.2.dist-info/WHEEL
litbee-0.1.2.dist-info/METADATA
litbee-0.1.2.dist-info/RECORD
